{
  "name": "Rogue",
  "race": "Human",
  "subrace": "",
  "class": "Rogue",
  "subclass": "Thief",
  "background": "",
  "alignment": "Lawful Neutral",
  "level": 4,
  "abilityScores": {
    "str": 8,
    "dex": 17,
    "con": 14,
    "int": 12,
    "wis": 13,
    "cha": 10
  },
  "hp": {
    "max": 31,
    "hitDiceType": 8,
    "hitDiceCount": 4,
    "hpHistory": [
      {
        "level": 2,
        "gained": 7,
        "method": "average",
        "notes": "5 (avg) + 2 CON"
      },
      {
        "level": 3,
        "gained": 7,
        "method": "average",
        "notes": "5 (avg) + 2 CON"
      },
      {
        "level": 4,
        "gained": 7,
        "method": "average",
        "notes": "5 (avg) + 2 CON"
      }
    ]
  },
  "proficiencyBonus": 2,
  "ac": 13,
  "speed": 25,
  "initiative": 3,
  "savingThrows": [
    "dex",
    "int"
  ],
  "skillProficiencies": [
    "acrobatics",
    "stealth",
    "perception",
    "deception"
  ],
  "cantripsKnown": [],
  "spellSlots": {},
  "preparedSpellCount": 0,
  "currentPreparedSpells": [],
  "domainSpells": [],
  "features": [
    "Sneak Attack",
    "Thieves' Cant",
    "Cunning Action",
    "Fast Hands",
    "Second-Story Work"
  ],
  "channelDivinityUses": 0,
  "equipment": "",
  "notes": "",
  "weapons": [
    {
      "name": "Dagger",
      "ability": "dex",
      "proficient": true,
      "damage": "1d8",
      "damageType": "",
      "notes": ""
    }
  ],
  "levelHistory": [
    {
      "level": 2,
      "from": 1,
      "hpMethod": "average",
      "hpRoll": null,
      "hpGained": 7,
      "retroHp": false,
      "retroHpAmount": 0
    },
    {
      "level": 3,
      "from": 2,
      "hpMethod": "average",
      "hpRoll": null,
      "hpGained": 7,
      "retroHp": false,
      "retroHpAmount": 0
    },
    {
      "level": 4,
      "from": 3,
      "hpMethod": "average",
      "hpRoll": null,
      "hpGained": 7,
      "retroHp": false,
      "retroHpAmount": 0,
      "asi": {
        "type": "plus2",
        "ability": "dex"
      }
    }
  ],
  "expertiseSkills": [
    "stealth",
    "perception"
  ],
  "resources": {},
  "currency": {
    "cp": 0,
    "sp": 0,
    "ep": 0,
    "gp": 0,
    "pp": 0
  },
  "id": "mnajn080rkrta",
  "currentHp": 31,
  "tempHp": 0,
  "spellSlotsUsed": {},
  "channelDivinityUsed": 0,
  "equippedItems": [],
  "quickItems": [],
  "bulkGear": "",
  "colorTheme": {
    "name": "Rogue Purple",
    "accent": "#9a6ac5",
    "accentHover": "#aa7ad5",
    "accentDim": "#6a4890",
    "bg": "#16121a",
    "surface": "#1e1a24",
    "surfaceRaised": "#28222e",
    "border": "#362e3d",
    "text": "#dcd0e8",
    "textDim": "#9888a8",
    "error": "#c45a5a",
    "success": "#6aaa5a",
    "inputBg": "#1a141e"
  },
  "deathSaves": {
    "successes": 0,
    "failures": 0
  },
  "concentration": {
    "active": false,
    "spellName": ""
  },
  "activeConditions": [],
  "sessionLog": [
    {
      "time": "9:28 AM",
      "text": "Sneak Attack: +8 (2d6). Total: 16"
    },
    {
      "time": "9:28 AM",
      "text": "Dagger — Damage: 8"
    },
    {
      "time": "9:28 AM",
      "text": "Dagger — Attack: 13"
    },
    {
      "time": "9:28 AM",
      "text": "Sneak Attack: +5 (2d6). Total: 9"
    },
    {
      "time": "9:28 AM",
      "text": "Dagger — Damage: 4"
    },
    {
      "time": "9:28 AM",
      "text": "Dagger — Attack: 16"
    },
    {
      "time": "9:28 AM",
      "text": "Healed 68 HP — HP 10→31"
    }
  ],
  "inspiration": false,
  "journal": [],
  "externalBuffs": [],
  "maxHpBoost": {
    "value": 0,
    "source": ""
  },
  "spellbook": [],
  "spellMastery": null,
  "signatureSpells": null,
  "passwordHash": null
}